Metadata-Version: 2.1
Name: octohot
Version: 0.0.9
Summary: A git command automation for multiple repositories
Home-page: https://github.com/Hotmart-Org/octohot
Author: Jônatas Renan Camilo Alves
Author-email: jonatas.alves@hotmart.com
License: UNKNOWN
Keywords: git automation github repositories
Platform: UNKNOWN
Classifier: Development Status :: 5 - Production/Stable
Classifier: Intended Audience :: Developers
Classifier: License :: OSI Approved :: GNU General Public License v3 (GPLv3)
Classifier: Programming Language :: Python :: 3
Classifier: Topic :: Software Development :: Libraries :: Python Modules
Classifier: Topic :: Utilities
